{
  "db_name": "PostgreSQL",
  "query": "\n            SELECT\n                l1_batch_number, status, verifier_picked_at, verifier_submit_at\n            FROM\n                proof_offchain_verification_details\n            WHERE\n                l1_batch_number = $1\n            ",
  "describe": {
    "columns": [
      {
        "ordinal": 0,
        "name": "l1_batch_number",
        "type_info": "Int8"
      },
      {
        "ordinal": 1,
        "name": "status",
        "type_info": "Text"
      },
      {
        "ordinal": 2,
        "name": "verifier_picked_at",
        "type_info": "Timestamp"
      },
      {
        "ordinal": 3,
        "name": "verifier_submit_at",
        "type_info": "Timestamp"
      }
    ],
    "parameters": {
      "Left": [
        "Int8"
      ]
    },
    "nullable": [
      false,
      false,
      true,
      true
    ]
  },
  "hash": "d4b7c848add81fd80a06bd31ddf8213c4a4b8d88b3771a3b89c3c9b8bbde1050"
}
